README.md
setup.py
autotrainz/__init__.py
autotrainz/main.py
autotrainz/project_config.py
autotrainz.egg-info/PKG-INFO
autotrainz.egg-info/SOURCES.txt
autotrainz.egg-info/dependency_links.txt
autotrainz.egg-info/top_level.txt
autotrainz/builders_and_generators/__init__.py
autotrainz/builders_and_generators/base.py
autotrainz/builders_and_generators/build_pipeline.py
autotrainz/builders_and_generators/build_step.py
autotrainz/builders_and_generators/builder.py
autotrainz/builders_and_generators/director.py
autotrainz/builders_and_generators/orchestration_artifact_builder/__init__.py
autotrainz/builders_and_generators/orchestration_artifact_builder/airflow_artifact_builder.py
autotrainz/builders_and_generators/orchestration_artifact_builder/argo_artifact_builder.py
autotrainz/builders_and_generators/orchestration_artifact_builder/file_artifact_builder.py
autotrainz/builders_and_generators/orchestration_artifact_builder/orchestration_artifact_builder.py
autotrainz/builders_and_generators/orchestration_artifact_builder/artifact_cmd_builder/__init__.py
autotrainz/builders_and_generators/orchestration_artifact_builder/artifact_cmd_builder/artifact_cmd_builder.py
autotrainz/builders_and_generators/orchestration_artifact_builder/artifact_cmd_builder/python_cmd_builder.py
autotrainz/builders_and_generators/orchestration_artifact_builder/artifact_cmd_builder/sparkk8_cmd_builder.py
autotrainz/builders_and_generators/orhcestration_artifact_deployer/__init__.py
autotrainz/builders_and_generators/orhcestration_artifact_deployer/airflow_deployer.py
autotrainz/builders_and_generators/orhcestration_artifact_deployer/argo_deployer.py
autotrainz/builders_and_generators/orhcestration_artifact_deployer/file_deployer.py
autotrainz/builders_and_generators/orhcestration_artifact_deployer/gcs_airflow_deployer.py
autotrainz/builders_and_generators/orhcestration_artifact_deployer/orchestration_artifact_deployer.py
autotrainz/builders_and_generators/orhcestration_artifact_deployer/artifact_registries/__init__.py
autotrainz/builders_and_generators/orhcestration_artifact_deployer/artifact_registries/artifact_registry.py
